fund_my_watcard/__init__.py
fund_my_watcard/config_file.py
fund_my_watcard/log.py
fund_my_watcard/main.py
fund_my_watcard/messages.py
fund_my_watcard/mywatcard.py
fund_my_watcard/transaction.py
fund_my_watcard/util.py
fund_my_watcard/version.py
fund_my_watcard-0.5.1.dist-info/LICENSE
fund_my_watcard-0.5.1.dist-info/METADATA
fund_my_watcard-0.5.1.dist-info/WHEEL
fund_my_watcard-0.5.1.dist-info/entry_points.txt
fund_my_watcard-0.5.1.dist-info/top_level.txt
fund_my_watcard-0.5.1.dist-info/RECORD
