Metadata-Version: 2.1
Name: fund-my-watcard
Version: 0.5.1
Summary: A tool to fund WatCard in an easy way
Home-page: https://github.com/xingweitian/fund-my-watcard
Author: xingweitian, faushine, KevinLu
Author-email: xingweitian@gmail.com
License: GPL-3.0
Keywords: WatCard
Platform: UNKNOWN
Classifier: License :: OSI Approved :: GNU General Public License v3 (GPLv3)
Classifier: Programming Language :: Python :: 3.5
Classifier: Programming Language :: Python :: 3.6
Classifier: Programming Language :: Python :: 3.7
Requires-Python: >=3.5
Requires-Dist: splinter (==0.11.0)
Requires-Dist: webdriver-manager (==2.2.0)
Requires-Dist: cryptography (==2.8)
Requires-Dist: prettytable (==0.7.2)
Requires-Dist: colorlog (==4.0.2)
